solar/__init__.py
solar/cli.py
solar/engine.py
solar_lang-1.0.4.dist-info/licenses/LICENSE
solar_lang-1.0.4.dist-info/METADATA
solar_lang-1.0.4.dist-info/WHEEL
solar_lang-1.0.4.dist-info/entry_points.txt
solar_lang-1.0.4.dist-info/top_level.txt
solar_lang-1.0.4.dist-info/RECORD
