Metadata-Version: 2.4
Name: solar-lang
Version: 1.0.4
Summary: Solar programming language CLI
Author: Dawid Pszeniczny
License: MIT
Requires-Python: >=3.9
License-File: LICENSE
Requires-Dist: customtkinter>=5.2.0
Requires-Dist: pygame>=2.0
Dynamic: license-file
